<?xml version="1.0" encoding="UTF-8"?>
<profile>
	<name>BMW</name>
	<indicator>
		<name>panel</name>
		<x>115</x>
		<y>130</y>
	</indicator>
	<indicator>
		<name>speedometer</name>
		<x>40</x>
		<y>150</y>
	</indicator>
	<indicator>
		<name>fuelSensor</name>
		<x>115</x>
		<y>130</y>
	</indicator>
	<indicator>
		<name>oilSensor</name>
		<x>40</x>
		<y>150</y>
	</indicator>
	<indicator>
		<name>helm</name>
		<x>115</x>
		<y>130</y>
	</indicator>
	<indicator>
		<name>righTurnSignal</name>
		<x>40</x>
		<y>150</y>
	</indicator>
	<indicator>
		<name>lefTurnSignal</name>
		<x>115</x>
		<y>130</y>
	</indicator>
	<indicator>
		<name>conditioner</name>
		<x>40</x>
		<y>150</y>
	</indicator>	
	<indicator>
		<name>radio</name>
		<x>0</x>
		<y>0</y>
	</indicator>
	<indicator>
		<name>browser</name>
		<x>0</x>
		<y>0</y>
	</indicator>
</profile>
